ox_cache
