Metadata-Version: 1.1
Name: ox-cache
Version: 1.3.1
Summary: Tools for caching and memoization in python.
Home-page: http://github.com/emin63/ox_cache
Author: Emin Martinian
Author-email: emin.martinian@gmail.com
License: MIT
Keywords: cache caching memoization
Platform: UNKNOWN
Classifier: Development Status :: 3 - Alpha
Classifier: Intended Audience :: Developers
Classifier: Programming Language :: Python :: 3
